ebilab/__init__.py
ebilab/__main__.py
ebilab/_cli.py
ebilab/icon.ico
ebilab/project.py
ebilab/py.typed
ebilab/analysis/__init__.py
ebilab/analysis/_actions.py
ebilab/analysis/_preprocess.py
ebilab/analysis/_process.py
ebilab/analysis2/__init__.py
ebilab/analysis2/base.py
ebilab/analysis2/manifest.py
ebilab/analysis2/options.py
ebilab/analysis2/process.py
ebilab/analysis2/project.py
ebilab/analysis2/subproject.py
ebilab/analysis2/tests/__init__.py
ebilab/analysis2/tests/test_options.py
ebilab/analysis2/tests/test_plotter.py
ebilab/analysis2/ui/__init__.py
ebilab/analysis2/ui/clipboard.py
ebilab/analysis2/ui/view.py
ebilab/data/project-template/.gitignore
ebilab/data/project-template/ebilab.ini
ebilab/data/project-template/main.py
ebilab/data/project-template/data/input/.gitignore
ebilab/data/project-template/data/original/.gitignore
ebilab/data/project-template/data/output/.gitignore
ebilab/data/project-template/data/plot/.gitignore
ebilab/experiment/__init__.py
ebilab/experiment/_experiment_controller.py
ebilab/experiment/_experiment_manager.py
ebilab/experiment/_ui_tkinter.py
ebilab/experiment/options.py
ebilab/experiment/protocol.py
ebilab/experiment/util.py
ebilab/experiment/devices/__init__.py
ebilab/experiment/devices/visa.py
ebilab/experiment/devices/_visa/A707.py
ebilab/experiment/devices/_visa/E4980.py
ebilab/experiment/devices/_visa/K34411A.py
ebilab/experiment/devices/_visa/__init__.py
ebilab-2.9.0.dist-info/licenses/LICENSE
ebilab-2.9.0.dist-info/METADATA
ebilab-2.9.0.dist-info/WHEEL
ebilab-2.9.0.dist-info/entry_points.txt
ebilab-2.9.0.dist-info/top_level.txt
ebilab-2.9.0.dist-info/RECORD
