Metadata-Version: 2.4
Name: ebilab
Version: 2.9.0
Summary: Python package for my research
Home-page: https://ebilab.readthedocs.io/
Author: Yusuke Ebihara
Author-email: yusuke@ebihara.me
Project-URL: GitHub repository, https://github.com/ebiyuu1121/ebilab
Classifier: Programming Language :: Python :: 3.8
Classifier: License :: OSI Approved :: MIT License
Classifier: Operating System :: OS Independent
License-File: LICENSE
Requires-Dist: tqdm
Requires-Dist: numpy
Requires-Dist: pandas
Requires-Dist: matplotlib
Requires-Dist: watchdog
Requires-Dist: click
Requires-Dist: pyvisa
Requires-Dist: GitPython
Requires-Dist: chardet
Requires-Dist: pyyaml
Requires-Dist: pywin32; os_name == "nt"
Dynamic: author
Dynamic: author-email
Dynamic: classifier
Dynamic: description-content-type
Dynamic: home-page
Dynamic: license-file
Dynamic: project-url
Dynamic: requires-dist
Dynamic: summary
